full_yaml_metadata.py
markdown_full_yaml_metadata-2.2.1.dist-info/METADATA
markdown_full_yaml_metadata-2.2.1.dist-info/LICENSE
markdown_full_yaml_metadata-2.2.1.dist-info/WHEEL
markdown_full_yaml_metadata-2.2.1.dist-info/RECORD
