Metadata-Version: 2.1
Name: markdown-full-yaml-metadata
Version: 2.2.1
Summary: YAML metadata extension for Python-Markdown
Home-page: https://github.com/sivakov512/python-markdown-full-yaml-metadata
License: MIT
Author: Nikita Sivakov
Author-email: sivakov512@icloud.com
Requires-Python: >=3.8.1,<4.0.0
Classifier: License :: OSI Approved :: MIT License
Classifier: Programming Language :: Python :: 3
Classifier: Programming Language :: Python :: 3.9
Classifier: Programming Language :: Python :: 3.10
Classifier: Programming Language :: Python :: 3.11
Requires-Dist: markdown (>=3.4.1,<4.0.0)
Requires-Dist: pyyaml (>=6.0,<7.0)
Project-URL: Repository, https://github.com/sivakov512/python-markdown-full-yaml-metadata
